[{"title": "Things Fall Apart", "description": "Things Fall Apart", "userId": 158}, {"title": "Fairy tales", "description": "Fairy tales", "userId": 136}, {"title": "The Divine Comedy", "description": "The Divine Comedy", "userId": 349}, {"title": "The Epic Of Gilgamesh", "description": "The Epic Of Gilgamesh", "userId": 136}, {"title": "The Book Of Job", "description": "The Book Of Job", "userId": 133}, {"title": "One Thousand and One Nights", "description": "One Thousand and One Nights", "userId": 242}, {"title": "Nj\u00e1l's Saga", "description": "Nj\u00e1l's Saga", "userId": 398}, {"title": "Pride and Prejudice", "description": "Pride and Prejudice", "userId": 173}, {"title": "Le P\u00e8re Goriot", "description": "Le P\u00e8re Goriot", "userId": 485}, {"title": "Molloy, Malone Dies, The Unnamable, the trilogy", "description": "Molloy, Malone Dies, The Unnamable, the trilogy", "userId": 469}, {"title": "The Decameron", "description": "The Decameron", "userId": 153}, {"title": "Ficciones", "description": "Ficciones", "userId": 368}, {"title": "Wuthering Heights", "description": "Wuthering Heights", "userId": 404}, {"title": "The Stranger", "description": "The Stranger", "userId": 331}, {"title": "Poems", "description": "Poems", "userId": 457}, {"title": "Journey to the End of the Night", "description": "Journey to the End of the Night", "userId": 51}, {"title": "Don Quijote De La Mancha", "description": "Don Quijote De La Mancha", "userId": 425}, {"title": "The Canterbury Tales", "description": "The Canterbury Tales", "userId": 12}, {"title": "Stories", "description": "Stories", "userId": 78}, {"title": "Nostromo", "description": "Nostromo", "userId": 307}, {"title": "Great Expectations", "description": "Great Expectations", "userId": 165}, {"title": "Jacques the Fatalist", "description": "Jacques the Fatalist", "userId": 305}, {"title": "Berlin Alexanderplatz", "description": "Berlin Alexanderplatz", "userId": 135}, {"title": "Crime and Punishment", "description": "Crime and Punishment", "userId": 253}, {"title": "The Idiot", "description": "The Idiot", "userId": 36}, {"title": "The Possessed", "description": "The Possessed", "userId": 53}, {"title": "The Brothers Karamazov", "description": "The Brothers Karamazov", "userId": 318}, {"title": "Middlemarch", "description": "Middlemarch", "userId": 354}, {"title": "Invisible Man", "description": "Invisible Man", "userId": 220}, {"title": "Medea", "description": "Medea", "userId": 369}, {"title": "Absalom, Absalom!", "description": "Absalom, Absalom!", "userId": 371}, {"title": "The Sound and the Fury", "description": "The Sound and the Fury", "userId": 123}, {"title": "Madame Bovary", "description": "Madame Bovary", "userId": 226}, {"title": "Sentimental Education", "description": "Sentimental Education", "userId": 191}, {"title": "Gypsy Ballads", "description": "Gypsy Ballads", "userId": 382}, {"title": "One Hundred Years of Solitude", "description": "One Hundred Years of Solitude", "userId": 231}, {"title": "Love in the Time of Cholera", "description": "Love in the Time of Cholera", "userId": 181}, {"title": "Faust", "description": "Faust", "userId": 340}, {"title": "Dead Souls", "description": "Dead Souls", "userId": 434}, {"title": "The Tin Drum", "description": "The Tin Drum", "userId": 37}, {"title": "The Devil to Pay in the Backlands", "description": "The Devil to Pay in the Backlands", "userId": 58}, {"title": "Hunger", "description": "Hunger", "userId": 221}, {"title": "The Old Man and the Sea", "description": "The Old Man and the Sea", "userId": 337}, {"title": "Iliad", "description": "Iliad", "userId": 326}, {"title": "Odyssey", "description": "Odyssey", "userId": 313}, {"title": "A Doll's House", "description": "A Doll's House", "userId": 92}, {"title": "Ulysses", "description": "Ulysses", "userId": 242}, {"title": "Stories", "description": "Stories", "userId": 447}, {"title": "The Trial", "description": "The Trial", "userId": 461}, {"title": "The Castle", "description": "The Castle", "userId": 151}, {"title": "The recognition of Shakuntala", "description": "The recognition of Shakuntala", "userId": 198}, {"title": "The Sound of the Mountain", "description": "The Sound of the Mountain", "userId": 53}, {"title": "Zorba the Greek", "description": "Zorba the Greek", "userId": 433}, {"title": "Sons and Lovers", "description": "Sons and Lovers", "userId": 451}, {"title": "Independent People", "description": "Independent People", "userId": 386}, {"title": "Poems", "description": "Poems", "userId": 68}, {"title": "The Golden Notebook", "description": "The Golden Notebook", "userId": 123}, {"title": "Pippi Longstocking", "description": "Pippi Longstocking", "userId": 434}, {"title": "Diary of a Madman", "description": "Diary of a Madman", "userId": 85}, {"title": "Children of Gebelawi", "description": "Children of Gebelawi", "userId": 234}, {"title": "Buddenbrooks", "description": "Buddenbrooks", "userId": 253}, {"title": "The Magic Mountain", "description": "The Magic Mountain", "userId": 31}, {"title": "Moby Dick", "description": "Moby Dick", "userId": 253}, {"title": "Essays", "description": "Essays", "userId": 312}, {"title": "History", "description": "History", "userId": 486}, {"title": "Beloved", "description": "Beloved", "userId": 249}, {"title": "The Tale of Genji", "description": "The Tale of Genji", "userId": 161}, {"title": "The Man Without Qualities", "description": "The Man Without Qualities", "userId": 276}, {"title": "Lolita", "description": "Lolita", "userId": 483}, {"title": "Nineteen Eighty-Four", "description": "Nineteen Eighty-Four", "userId": 442}, {"title": "Metamorphoses", "description": "Metamorphoses", "userId": 242}, {"title": "The Book of Disquiet", "description": "The Book of Disquiet", "userId": 443}, {"title": "Tales", "description": "Tales", "userId": 46}, {"title": "In Search of Lost Time", "description": "In Search of Lost Time", "userId": 23}, {"title": "Gargantua and Pantagruel", "description": "Gargantua and Pantagruel", "userId": 92}, {"title": "Pedro P\u00e1ramo", "description": "Pedro P\u00e1ramo", "userId": 28}, {"title": "The Masnavi", "description": "The Masnavi", "userId": 327}, {"title": "Midnight's Children", "description": "Midnight's Children", "userId": 184}, {"title": "Bostan", "description": "Bostan", "userId": 166}, {"title": "Season of Migration to the North", "description": "Season of Migration to the North", "userId": 198}, {"title": "Blindness", "description": "Blindness", "userId": 112}, {"title": "Hamlet", "description": "Hamlet", "userId": 92}, {"title": "King Lear", "description": "King Lear", "userId": 158}, {"title": "Othello", "description": "Othello", "userId": 286}, {"title": "Oedipus the King", "description": "Oedipus the King", "userId": 358}, {"title": "The Red and the Black", "description": "The Red and the Black", "userId": 211}, {"title": "The Life And Opinions of Tristram Shandy", "description": "The Life And Opinions of Tristram Shandy", "userId": 275}, {"title": "Confessions of Zeno", "description": "Confessions of Zeno", "userId": 367}, {"title": "Gulliver's Travels", "description": "Gulliver's Travels", "userId": 253}, {"title": "War and Peace", "description": "War and Peace", "userId": 176}, {"title": "Anna Karenina", "description": "Anna Karenina", "userId": 463}, {"title": "The Death of Ivan Ilyich", "description": "The Death of Ivan Ilyich", "userId": 478}, {"title": "The Adventures of Huckleberry Finn", "description": "The Adventures of Huckleberry Finn", "userId": 189}, {"title": "Ramayana", "description": "Ramayana", "userId": 201}, {"title": "The Aeneid", "description": "The Aeneid", "userId": 128}, {"title": "Mahabharata", "description": "Mahabharata", "userId": 456}, {"title": "Leaves of Grass", "description": "Leaves of Grass", "userId": 16}, {"title": "Mrs Dalloway", "description": "Mrs Dalloway", "userId": 411}, {"title": "To the Lighthouse", "description": "To the Lighthouse", "userId": 107}, {"title": "Memoirs of Hadrian", "description": "Memoirs of Hadrian", "userId": 343}]